README.txt
setup.cfg
setup.py
docs/AUTHORS.txt
docs/CHANGES.txt
docs/INSTALL.txt
docs/LICENSE.txt
p4a/__init__.py
p4a.audio.egg-info/PKG-INFO
p4a.audio.egg-info/SOURCES.txt
p4a.audio.egg-info/dependency_links.txt
p4a.audio.egg-info/entry_points.txt
p4a.audio.egg-info/namespace_packages.txt
p4a.audio.egg-info/not-zip-safe
p4a.audio.egg-info/requires.txt
p4a.audio.egg-info/top_level.txt
p4a/audio/__init__.py
p4a/audio/audioanno.py
p4a/audio/configure.zcml
p4a/audio/genre.py
p4a/audio/interfaces.py
p4a/audio/media-player.txt
p4a/audio/media.py
p4a/audio/migration.py
p4a/audio/migration.txt
p4a/audio/p4a-audio.txt
p4a/audio/utils.py
p4a/audio/browser/__init__.py
p4a/audio/browser/audio-album.pt
p4a/audio/browser/audio-container.pt
p4a/audio/browser/audio-edit.pt
p4a/audio/browser/audio-listed-single.pt
p4a/audio/browser/audio-tracklisting-single.pt
p4a/audio/browser/audio.pt
p4a/audio/browser/audio.py
p4a/audio/browser/audiocd-popup.pt
p4a/audio/browser/cd_playlist.xspf.pt
p4a/audio/browser/configure.zcml
p4a/audio/browser/displays.py
p4a/audio/browser/media.py
p4a/audio/browser/popup-play.pt
p4a/audio/browser/support.py
p4a/audio/browser/widget.py
p4a/audio/browser/resources/audioimages/audio.gif
p4a/audio/browser/resources/audioimages/audio_icon.gif
p4a/audio/browser/resources/audioimages/comments.gif
p4a/audio/browser/resources/audioimages/download_icon.gif
p4a/audio/browser/resources/audioimages/download_icon.png
p4a/audio/browser/resources/audioimages/download_icon_old.gif
p4a/audio/browser/resources/audioimages/feed-icon.png
p4a/audio/browser/resources/audioimages/flash_play_icon.gif
p4a/audio/browser/resources/audioimages/play_icon.gif
p4a/audio/browser/resources/audioimages/play_icon.png
p4a/audio/browser/resources/audioimages/play_icon_old.gif
p4a/audio/browser/resources/audioimages/podcast_icon.png
p4a/audio/browser/resources/audioimages/popup_play_icon.gif
p4a/audio/browser/resources/audioimages/popup_play_icon.png
p4a/audio/browser/resources/audioimages/popup_play_icon_old.gif
p4a/audio/browser/resources/audioimages/ratings.gif
p4a/audio/browser/resources/audioimages/rss2_icon.png
p4a/audio/browser/resources/audioimages/small_gray_star.gif
p4a/audio/browser/resources/audioimages/small_yellow_star.gif
